flyworks_mcp/__init__.py
flyworks_mcp/__main__.py
flyworks_mcp/server.py
flyworks_mcp/assets/__init__.py
flyworks_mcp/assets/avatar.mp4
flyworks_mcp/assets/avatar.png
flyworks_mcp/assets/intro.mp3
iflow_mcp_flyworks_mcp-0.2.3.dist-info/licenses/LICENSE
iflow_mcp_flyworks_mcp-0.2.3.dist-info/METADATA
iflow_mcp_flyworks_mcp-0.2.3.dist-info/WHEEL
iflow_mcp_flyworks_mcp-0.2.3.dist-info/entry_points.txt
iflow_mcp_flyworks_mcp-0.2.3.dist-info/top_level.txt
iflow_mcp_flyworks_mcp-0.2.3.dist-info/RECORD
